{"appVersion":"3.0.0","author":"买菜助手","desc":"系统不得低于安卓 8.0 ","failDuration":10000,"failIsAlarm":true,"id":"92db64b0-34e0-439e-88ff-4b8646d5e327","launchTime":25,"name":"实例 - 点击屏幕","stepDelay":100,"steps":[{"condList":[{"node":{"className":"","coordinate":"","id":"com.univerindream.maicaiassistant:id/help","index":0,"isCheckable":null,"isChecked":null,"isClickable":null,"isEditable":null,"isEnabled":null,"isFocused":null,"isScrollable":null,"isSelected":null,"isVisibleToUser":null,"packageName":"","txt":""},"type":"NODE_IS_MATCH"}],"failBackCount":1,"handle":{"delayRunAfter":0,"delayRunBefore":100,"node":{"className":"","coordinate":"1008.0,156.0","id":"","index":0,"isCheckable":null,"isChecked":null,"isClickable":null,"isEditable":null,"isEnabled":null,"isFocused":null,"isScrollable":null,"isSelected":null,"isVisibleToUser":null,"packageName":"","txt":""},"type":"CLICK_SCREEN"},"isAlarm":false,"isEnable":true,"isExecuteOnce":false,"isFailBack":false,"isManual":false,"isRepeat":false,"name":"点击右上角 - 如果存在问号"}],"updateDateStr":"2022-05-05 00:27:13"}